Metadata-Version: 1.0
Name: bio-assembly-refinement
Version: 0.3.3
Summary: Assembly refinement tools, mostly useful for (but not limited to) pacbio bacterial assembly
Home-page: https://github.com/nds/bio_assembly_refinement
Author: Nishadi De Silva
Author-email: nds@sanger.ac.uk
License: GPLv3
Platform: UNKNOWN
